predict_gbm/.gitignore
predict_gbm/__init__.py
predict_gbm/base.py
predict_gbm/data/datasets/lumiere.json
predict_gbm/data/datasets/predict_gbm.json
predict_gbm/data/datasets/rhuh.json
predict_gbm/data/datasets/tum_gbm.json
predict_gbm/data/mni152_atlas/mni_icbm152_csf_pbmap.nii.gz
predict_gbm/data/mni152_atlas/mni_icbm152_gm_pbmap.nii.gz
predict_gbm/data/mni152_atlas/mni_icbm152_t1.nii.gz
predict_gbm/data/mni152_atlas/mni_icbm152_t1_brain_mask.nii.gz
predict_gbm/data/mni152_atlas/mni_icbm152_t1_stripped.nii.gz
predict_gbm/data/mni152_atlas/mni_icbm152_tissues.nii.gz
predict_gbm/data/mni152_atlas/mni_icbm152_wm_pbmap.nii.gz
predict_gbm/data/models/test_model.tar
predict_gbm/data/sri24_atlas/pbmap_csf.nii.gz
predict_gbm/data/sri24_atlas/pbmap_gm.nii.gz
predict_gbm/data/sri24_atlas/pbmap_wm.nii.gz
predict_gbm/data/sri24_atlas/t1_stripped.nii.gz
predict_gbm/data/sri24_atlas/tissues.nii.gz
predict_gbm/data/sri24_atlas/tissues_dilated.nii.gz
predict_gbm/evaluation/__init__.py
predict_gbm/evaluation/evaluate.py
predict_gbm/evaluation/metrics.py
predict_gbm/pipeline.py
predict_gbm/prediction/__init__.py
predict_gbm/prediction/docker_funcs.py
predict_gbm/prediction/growth_model.py
predict_gbm/prediction/predict.py
predict_gbm/preprocessing/__init__.py
predict_gbm/preprocessing/dicom_to_nifti.py
predict_gbm/preprocessing/norm_ss_coregistration.py
predict_gbm/preprocessing/preprocess.py
predict_gbm/preprocessing/tissue_segmentation.py
predict_gbm/preprocessing/tumor_segmentation.py
predict_gbm/utils/__init__.py
predict_gbm/utils/constants.py
predict_gbm/utils/parsing.py
predict_gbm/utils/utils.py
predict_gbm/utils/visualization.py
predict_gbm-0.1.0.dist-info/LICENCE
predict_gbm-0.1.0.dist-info/METADATA
predict_gbm-0.1.0.dist-info/WHEEL
predict_gbm-0.1.0.dist-info/RECORD
