Metadata-Version: 2.3
Name: predict-gbm
Version: 0.1.0
Summary: Tools for processing MRI images and evaluating tumor growth models via radiation plans.
Keywords: brain tumor,glioma
Author: Lucas Zimmer
Author-email: zimmer.lucas.w@gmail.com
Requires-Python: >=3.10,<4.0
Classifier: Programming Language :: Python :: 3
Classifier: Programming Language :: Python :: 3.10
Classifier: Programming Language :: Python :: 3.11
Classifier: Programming Language :: Python :: 3.12
Classifier: Programming Language :: Python :: 3.13
Requires-Dist: brainles-preprocessing (>=0.6.2,<0.7.0)
Requires-Dist: brats (>=0.0.28,<0.0.29)
Requires-Dist: pydicom (>=3.0.1,<4.0.0)
Requires-Dist: pypdf (>=6.0.0,<7.0.0)
Requires-Dist: typing-extensions (>=4.14.1,<5.0.0)
Requires-Dist: wandb (>=0.21.1,<0.22.0)
Project-URL: Repository, https://github.com/BrainLesion/PredictGBM
